qa_store/__init__.py
qa_store/helpers.py
qa_store/qa_kb.py
qa_store/qa_system.py
qa_store/qa_tree.py
qa_store-0.2.1.dist-info/METADATA
qa_store-0.2.1.dist-info/WHEEL
qa_store-0.2.1.dist-info/licenses/LICENSE
qa_store-0.2.1.dist-info/RECORD
