Metadata-Version: 2.3
Name: qa-store
Version: 0.2.1
Summary: Like a key-value store, but for questions and answers.
Project-URL: GitHub, https://github.com/witt3rd/qa-store
Author-email: Donald Thompson <witt3rd@witt3rd.com>
License-File: LICENSE
Requires-Python: >=3.8
Requires-Dist: chromadb>=0.5.3
Requires-Dist: graphviz>=0.20.3
Requires-Dist: litellm>=1.41.6
Requires-Dist: loguru>=0.7.2
Requires-Dist: openai>=1.35.10
Requires-Dist: python-dotenv>=1.0.1
Requires-Dist: sentence-transformers>=3.0.1
